hydrorolldemo-0.1.0.dist-info/METADATA
hydrorolldemo-0.1.0.dist-info/WHEEL
hydrorolldemo/__init__.py
hydrorolldemo/hydrorolldemo.cp311-win_amd64.pyd
hydrorolldemo-0.1.0.dist-info/RECORD
