Metadata-Version: 2.1
Name: hydrorolldemo
Version: 0.1.0
Classifier: License :: OSI Approved :: MIT License
Classifier: Development Status :: 3 - Alpha
Classifier: Intended Audience :: Developers
Classifier: Programming Language :: Python
Classifier: Programming Language :: Rust
Classifier: Operating System :: POSIX
Classifier: Operating System :: MacOS :: MacOS X
Requires-Dist: pytest >=3.2.5 ; extra == 'dev'
Requires-Dist: pytest-benchmark >=3.1.1 ; extra == 'dev'
Requires-Dist: pip >=8.1.2 ; extra == 'dev'
Provides-Extra: dev
